{"id": "1471903591145299979", "conversation_id": "1471903591145299979", "created_at": "2021-12-17 18:02:17 UTC", "date": "2021-12-17", "time": "18:02:17", "timezone": "+0000", "user_id": 1253886987238543363, "username": "uncoverintl", "name": "Uncover", "place": "", "tweet": "#Bitcoin Hints Bullish, But Why It’s Far From Fresh Rally  #crypto #cryptocurrencies #cryptonews  https://t.co/Ca0IJEhAPi", "language": "en", "mentions": [], "urls": ["https://ift.tt/3Fm3ENn"], "photos": [], "replies_count": 0, "retweets_count": 0, "likes_count": 0, "hashtags": ["bitcoin", "crypto", "cryptocurrencies", "cryptonews"], "cashtags": [], "link": "https://twitter.com/UncoverIntl/status/1471903591145299979", "retweet": false, "quote_url": "", "video": 0, "thumbnail": "", "near": "", "geo": "", "source": "", "user_rt_id": "", "user_rt": "", "retweet_id": "", "reply_to": [], "retweet_date": "", "translate": "", "trans_src": "", "trans_dest": ""}
{"id": "1471903525462552582", "conversation_id": "1471903525462552582", "created_at": "2021-12-17 18:02:01 UTC", "date": "2021-12-17", "time": "18:02:01", "timezone": "+0000", "user_id": 1144271538545410048, "username": "cardano_today", "name": "Cardano Today", "place": "", "tweet": "Cardano Requires Maximum Trust in Your Technical Analysis #crypto #cryptocurrency #cardano #ada #cryptonews  https://t.co/LsrfRZOaum", "language": "en", "mentions": [], "urls": ["https://j.mp/3F6wykn"], "photos": [], "replies_count": 1, "retweets_count": 0, "likes_count": 1, "hashtags": ["crypto", "cryptocurrency", "cardano", "ada", "cryptonews"], "cashtags": [], "link": "https://twitter.com/cardano_today/status/1471903525462552582", "retweet": false, "quote_url": "", "video": 0, "thumbnail": "", "near": "", "geo": "", "source": "", "user_rt_id": "", "user_rt": "", "retweet_id": "", "reply_to": [], "retweet_date": "", "translate": "", "trans_src": "", "trans_dest": ""}
{"id": "1471903421175320581", "conversation_id": "1471903421175320581", "created_at": "2021-12-17 18:01:36 UTC", "date": "2021-12-17", "time": "18:01:36", "timezone": "+0000", "user_id": 1144271538545410048, "username": "cardano_today", "name": "Cardano Today", "place": "", "tweet": "Is Cardano the Top Competitor to Ethereum? #crypto #cryptocurrency #cardano #ada #cryptonews  https://t.co/ka1Xep9eDZ", "language": "en", "mentions": [], "urls": ["https://j.mp/3p2RL9m"], "photos": [], "replies_count": 0, "retweets_count": 0, "likes_count": 0, "hashtags": ["crypto", "cryptocurrency", "cardano", "ada", "cryptonews"], "cashtags": [], "link": "https://twitter.com/cardano_today/status/1471903421175320581", "retweet": false, "quote_url": "", "video": 0, "thumbnail": "", "near": "", "geo": "", "source": "", "user_rt_id": "", "user_rt": "", "retweet_id": "", "reply_to": [], "retweet_date": "", "translate": "", "trans_src": "", "trans_dest": ""}
{"id": "1471903295769829377", "conversation_id": "1471903295769829377", "created_at": "2021-12-17 18:01:07 UTC", "date": "2021-12-17", "time": "18:01:07", "timezone": "+0000", "user_id": 1336791474801872897, "username": "coinlistingbot", "name": "New Coins Listing", "place": "", "tweet": "New listing on #Blockchain: https://t.co/uTiPNOesu7\rCoin: $NEAR\rPairs:\r#NEAR/#USD\r#newcoinlisting #newlisting #crypto #cryptonews", "language": "en", "mentions": [], "urls": ["https://exchange.blockchain.com/trade/signup?referrerUsername=pop9990"], "photos": [], "replies_count": 0, "retweets_count": 0, "likes_count": 0, "hashtags": ["blockchain", "near", "usd", "newcoinlisting", "newlisting", "crypto", "cryptonews"], "cashtags": ["near"], "link": "https://twitter.com/CoinListingBot/status/1471903295769829377", "retweet": false, "quote_url": "", "video": 0, "thumbnail": "", "near": "", "geo": "", "source": "", "user_rt_id": "", "user_rt": "", "retweet_id": "", "reply_to": [], "retweet_date": "", "translate": "", "trans_src": "", "trans_dest": ""}
{"id": "1471903212538056704", "conversation_id": "1471903212538056704", "created_at": "2021-12-17 18:00:47 UTC", "date": "2021-12-17", "time": "18:00:47", "timezone": "+0000", "user_id": 1373092259491549186, "username": "bag_dao", "name": "👜💰 Blockchain Adventurers Guild (BAG) 💰👜", "place": "", "tweet": "What's on the horizon for cryptocurrencies in 2022?   https://t.co/P4zuUCS0ia  #cryptocurrency #bitcoin #cryptonews #cryptotrading  https://t.co/UHhNyavKTy", "language": "en", "mentions": [], "urls": ["https://twitter.com/jamesvgingerich/status/1471572896824930309?s=20"], "photos": ["https://pbs.twimg.com/media/FG1ALBJXEAA0FCU.jpg"], "replies_count": 0, "retweets_count": 0, "likes_count": 0, "hashtags": ["cryptocurrency", "bitcoin", "cryptonews", "cryptotrading"], "cashtags": [], "link": "https://twitter.com/BAG_DAO/status/1471903212538056704", "retweet": false, "quote_url": "https://twitter.com/jamesvgingerich/status/1471572896824930309?s=20", "video": 1, "thumbnail": "https://pbs.twimg.com/media/FG1ALBJXEAA0FCU.jpg", "near": "", "geo": "", "source": "", "user_rt_id": "", "user_rt": "", "retweet_id": "", "reply_to": [], "retweet_date": "", "translate": "", "trans_src": "", "trans_dest": ""}
{"id": "1471903149103407110", "conversation_id": "1471903149103407110", "created_at": "2021-12-17 18:00:32 UTC", "date": "2021-12-17", "time": "18:00:32", "timezone": "+0000", "user_id": 1387530822404739079, "username": "cryptoacademy17", "name": "Crypto-Academy", "place": "", "tweet": "The CEO and Managing Director of Mubadala Investment Company, Khaldoon Al Mubarak, revealed in an interview with CNBC on December 13 that his organization is considering investing in the “crypto ecosystem.”  #crypto #cryptonews #bitcoin #dubai #cryptoacademy  https://t.co/XeOCThd7rT", "language": "en", "mentions": [], "urls": [], "photos": ["https://pbs.twimg.com/media/FG1AHPgWYAA77IF.jpg"], "replies_count": 0, "retweets_count": 0, "likes_count": 0, "hashtags": ["crypto", "cryptonews", "bitcoin", "dubai", "cryptoacademy"], "cashtags": [], "link": "https://twitter.com/CryptoAcademy17/status/1471903149103407110", "retweet": false, "quote_url": "", "video": 1, "thumbnail": "https://pbs.twimg.com/media/FG1AHPgWYAA77IF.jpg", "near": "", "geo": "", "source": "", "user_rt_id": "", "user_rt": "", "retweet_id": "", "reply_to": [], "retweet_date": "", "translate": "", "trans_src": "", "trans_dest": ""}
{"id": "1471903089837981699", "conversation_id": "1471903089837981699", "created_at": "2021-12-17 18:00:17 UTC", "date": "2021-12-17", "time": "18:00:17", "timezone": "+0000", "user_id": 1323762343302615040, "username": "news_of_bsc", "name": "BSC News", "place": "", "tweet": "Axie Community Mobilizes Relief Ops in the Philippines. Find out how you can help! @Axie_Queen  @nixeniego  @axiesisters  @gabusch  @YGGPilipinas  @kookoocryptotv  @Jihoz_Axie  @enjoicrypto   #BSCNews #NFTs #GameFi #Cryptocurrency #CryptoNews #BSC  https://t.co/R8B2zKDl97", "language": "en", "mentions": [{"screen_name": "axie_queen", "name": "👑 tq 🦇🔊", "id": "1393852959021146112"}, {"screen_name": "nixeniego", "name": "nixtape 🦇🔊", "id": "363481121"}, {"screen_name": "axiesisters", "name": "axiesisters", "id": "96165636"}, {"screen_name": "gabusch", "name": "gabby dizon | ygg 🛡️⚔️", "id": "2309701"}, {"screen_name": "yggpilipinas", "name": "yggpilipinas", "id": "1465520804066902016"}, {"screen_name": "kookoocryptotv", "name": "kookoo✨🎮🤝", "id": "1300111074704920581"}, {"screen_name": "jihoz_axie", "name": "the jiho🦇🔊", "id": "1009692722976788480"}, {"screen_name": "enjoicrypto", "name": "ξnjoi 💰👻💰", "id": "2747060533"}], "urls": ["https://www.bsc.news/post/axie-infinity-community-mobilizes-relief-operations-in-the-philippines"], "photos": [], "replies_count": 0, "retweets_count": 1, "likes_count": 8, "hashtags": ["bscnews", "nfts", "gamefi", "cryptocurrency", "cryptonews", "bsc"], "cashtags": [], "link": "https://twitter.com/news_of_bsc/status/1471903089837981699", "retweet": false, "quote_url": "", "video": 0, "thumbnail": "", "near": "", "geo": "", "source": "", "user_rt_id": "", "user_rt": "", "retweet_id": "", "reply_to": [], "retweet_date": "", "translate": "", "trans_src": "", "trans_dest": ""}
{"id": "1471903087061262338", "conversation_id": "1471903087061262338", "created_at": "2021-12-17 18:00:17 UTC", "date": "2021-12-17", "time": "18:00:17", "timezone": "+0000", "user_id": 2307190704, "username": "paxful", "name": "Paxful", "place": "", "tweet": "We’re only a week away from #Christmas, but the happenings in the #crypto world know no #holidays. 🎄 Before you head off for the #weekend, here are this week’s top crypto stories for you to check out.  #cryptonews #bitcoinnews #fintech #nft #bitcoin  https://t.co/SjE86HMGML", "language": "en", "mentions": [], "urls": [], "photos": ["https://pbs.twimg.com/tweet_video_thumb/FG1ADrkXsAEYW6o.jpg"], "replies_count": 0, "retweets_count": 0, "likes_count": 1, "hashtags": ["christmas", "crypto", "holidays", "weekend", "cryptonews", "bitcoinnews", "fintech", "nft", "bitcoin"], "cashtags": [], "link": "https://twitter.com/paxful/status/1471903087061262338", "retweet": false, "quote_url": "", "video": 1, "thumbnail": "https://pbs.twimg.com/tweet_video_thumb/FG1ADrkXsAEYW6o.jpg", "near": "", "geo": "", "source": "", "user_rt_id": "", "user_rt": "", "retweet_id": "", "reply_to": [], "retweet_date": "", "translate": "", "trans_src": "", "trans_dest": ""}
{"id": "1471903070946832394", "conversation_id": "1471903070946832394", "created_at": "2021-12-17 18:00:13 UTC", "date": "2021-12-17", "time": "18:00:13", "timezone": "+0000", "user_id": 1350638647238815751, "username": "stylycrypt", "name": "Stylycrypt", "place": "", "tweet": "Finance Redefined: 83% of 7-figure Millennials own crypto, Sen. Warren criticizes DeFi, Dec. 10–17     https://t.co/O0nLSlZi8w from Cointelegraph #definews #cryptonews #newscrypto #cryptocurrencynews", "language": "en", "mentions": [], "urls": ["https://cointelegraph.com/news/finance-redefined-83-of-7-figure-millennials-own-crypto-sen-warren-criticizes-defi-dec-10-17"], "photos": [], "replies_count": 0, "retweets_count": 0, "likes_count": 0, "hashtags": ["definews", "cryptonews", "newscrypto", "cryptocurrencynews"], "cashtags": [], "link": "https://twitter.com/stylycrypt/status/1471903070946832394", "retweet": false, "quote_url": "", "video": 0, "thumbnail": "", "near": "", "geo": "", "source": "", "user_rt_id": "", "user_rt": "", "retweet_id": "", "reply_to": [], "retweet_date": "", "translate": "", "trans_src": "", "trans_dest": ""}
{"id": "1471903061723561990", "conversation_id": "1471903061723561990", "created_at": "2021-12-17 18:00:11 UTC", "date": "2021-12-17", "time": "18:00:11", "timezone": "+0000", "user_id": 1143109825930375168, "username": "digitalmoneybo1", "name": "DigitalMoneyBox", "place": "", "tweet": "Senate hearing on stablecoins: Compliance anxiety and Republican pushback. Via Cointelegraph -  https://t.co/BL1vtNDXq3 #CryptocurrencyNews #cryptocurrency #Crypto #CryptoNews", "language": "en", "mentions": [], "urls": ["https://www.digitalmoneybox.com/news/cryptocurrency/senate-hearing-on-stablecoins-compliance-anxiety-and-republican-pushback"], "photos": [], "replies_count": 0, "retweets_count": 0, "likes_count": 0, "hashtags": ["cryptocurrencynews", "cryptocurrency", "crypto", "cryptonews"], "cashtags": [], "link": "https://twitter.com/DigitalMoneyBo1/status/1471903061723561990", "retweet": false, "quote_url": "", "video": 0, "thumbnail": "", "near": "", "geo": "", "source": "", "user_rt_id": "", "user_rt": "", "retweet_id": "", "reply_to": [], "retweet_date": "", "translate": "", "trans_src": "", "trans_dest": ""}
{"id": "1471903035110707207", "conversation_id": "1471903035110707207", "created_at": "2021-12-17 18:00:04 UTC", "date": "2021-12-17", "time": "18:00:04", "timezone": "+0000", "user_id": 1324663407669354496, "username": "sentinelbtc", "name": "BTCSentinel", "place": "", "tweet": "⬇️ Oltre il 90% delle Criptovalute listate su BTCSentinel (119 su 132) sono in perdita nell'ultima ora.  Aggiornamenti e Grafici su: -&gt;  https://t.co/uXNsnLbtyR &lt;- #Crypto #CryptoNews #criptovalute #fintech #altcoin", "language": "it", "mentions": [], "urls": ["https://www.btcsentinel.com/tutte-le-criptovalute-valore-in-tempo-reale"], "photos": [], "replies_count": 0, "retweets_count": 1, "likes_count": 0, "hashtags": ["crypto", "cryptonews", "criptovalute", "fintech", "altcoin"], "cashtags": [], "link": "https://twitter.com/SentinelBtc/status/1471903035110707207", "retweet": false, "quote_url": "", "video": 0, "thumbnail": "", "near": "", "geo": "", "source": "", "user_rt_id": "", "user_rt": "", "retweet_id": "", "reply_to": [], "retweet_date": "", "translate": "", "trans_src": "", "trans_dest": ""}
{"id": "1471903032870944771", "conversation_id": "1471903032870944771", "created_at": "2021-12-17 18:00:04 UTC", "date": "2021-12-17", "time": "18:00:04", "timezone": "+0000", "user_id": 1324663407669354496, "username": "sentinelbtc", "name": "BTCSentinel", "place": "", "tweet": "#BTCSentinel #PriceAlert:  ⬆️ Top Gainers 1h #NMR: 4,59% #YFI: 4,26%  ⬇️ Top Loosers 1h #GTC: -4,41% #GODS: -4,29% #GRT: -4,03% #AGLD: -3,88% #MCO2: -3,30% #LPT: -3,06%  Aggiornamenti e Grafici su: -&gt;  https://t.co/1le2phHnlF &lt;- #Crypto #CryptoNews #criptovalute #fintech #altcoin", "language": "fr", "mentions": [], "urls": ["https://www.btcsentinel.com"], "photos": [], "replies_count": 0, "retweets_count": 1, "likes_count": 0, "hashtags": ["btcsentinel", "pricealert", "nmr", "yfi", "gtc", "gods", "grt", "agld", "mco2", "lpt", "crypto", "cryptonews", "criptovalute", "fintech", "altcoin"], "cashtags": [], "link": "https://twitter.com/SentinelBtc/status/1471903032870944771", "retweet": false, "quote_url": "", "video": 0, "thumbnail": "", "near": "", "geo": "", "source": "", "user_rt_id": "", "user_rt": "", "retweet_id": "", "reply_to": [], "retweet_date": "", "translate": "", "trans_src": "", "trans_dest": ""}
{"id": "1471903021860859904", "conversation_id": "1471903021860859904", "created_at": "2021-12-17 18:00:01 UTC", "date": "2021-12-17", "time": "18:00:01", "timezone": "+0000", "user_id": 1271475157970956290, "username": "bitcoinw0rld", "name": "BitcoinWorld", "place": "", "tweet": "As Ethereum 2.0 comes close, two developments boosting #Ethereum  blockchain is revealed this week. #cryptocurrency #CryptoNews #Blockchain #ETH   https://t.co/G3hiG9ijWX", "language": "en", "mentions": [], "urls": ["https://bitcoinworld.co.in/ethereum-scalability-gets-boost-from-new-cosmos-mastercard-projects/"], "photos": [], "replies_count": 0, "retweets_count": 0, "likes_count": 1, "hashtags": ["ethereum", "cryptocurrency", "cryptonews", "blockchain", "eth"], "cashtags": [], "link": "https://twitter.com/BitcoinW0rld/status/1471903021860859904", "retweet": false, "quote_url": "", "video": 0, "thumbnail": "", "near": "", "geo": "", "source": "", "user_rt_id": "", "user_rt": "", "retweet_id": "", "reply_to": [], "retweet_date": "", "translate": "", "trans_src": "", "trans_dest": ""}
{"id": "1471902883872448524", "conversation_id": "1471902883872448524", "created_at": "2021-12-17 17:59:28 UTC", "date": "2021-12-17", "time": "17:59:28", "timezone": "+0000", "user_id": 1350638647238815751, "username": "stylycrypt", "name": "Stylycrypt", "place": "", "tweet": "Reddit’s Co-Founder, Polygon Pledge $200M for Web3 Social Media, Gaming   https://t.co/THmX4m8GRX from Decrypt #definews #cryptonews #newscrypto #cryptocurrencynews", "language": "en", "mentions": [], "urls": ["https://wp.decrypt.co/88620/reddit-cofounder-polygon-200m-web3-social-media-gaming/"], "photos": [], "replies_count": 0, "retweets_count": 0, "likes_count": 0, "hashtags": ["definews", "cryptonews", "newscrypto", "cryptocurrencynews"], "cashtags": [], "link": "https://twitter.com/stylycrypt/status/1471902883872448524", "retweet": false, "quote_url": "", "video": 0, "thumbnail": "", "near": "", "geo": "", "source": "", "user_rt_id": "", "user_rt": "", "retweet_id": "", "reply_to": [], "retweet_date": "", "translate": "", "trans_src": "", "trans_dest": ""}
